routelit_silicon/__init__.py
routelit_silicon/builder.py
routelit_silicon/static/frontend.css
routelit_silicon/static/routelit-silicon.es.js
routelit_silicon/static/routelit-silicon.es.js.map
routelit_silicon/static/routelit-silicon.umd.js
routelit_silicon/static/routelit-silicon.umd.js.map
routelit_silicon/static/vite.svg
routelit_silicon/static/.vite/manifest.json
routelit_silicon-0.2.3.dist-info/METADATA
routelit_silicon-0.2.3.dist-info/WHEEL
routelit_silicon-0.2.3.dist-info/licenses/LICENSE
routelit_silicon-0.2.3.dist-info/RECORD
