Metadata-Version: 2.4
Name: routelit-silicon
Version: 0.2.3
Summary: RouteLit Silicon is a Python library that extends RouteLit Builder with pre-built UI components and layouts.
Project-URL: Homepage, https://routelit.github.io/routelit-silicon/
Project-URL: Repository, https://github.com/routelit/routelit-silicon
Project-URL: Documentation, https://routelit.github.io/routelit-silicon/
Author-email: Rolando Gómez Tabar <rolangom@gmail.com>
License-File: LICENSE
Keywords: builder,components,python,react,routelit,silicon.css,ui
Classifier: Intended Audience :: Developers
Classifier: Programming Language :: Python
Classifier: Programming Language :: Python :: 3
Classifier: Programming Language :: Python :: 3.9
Classifier: Programming Language :: Python :: 3.10
Classifier: Programming Language :: Python :: 3.11
Classifier: Programming Language :: Python :: 3.12
Classifier: Programming Language :: Python :: 3.13
Classifier: Topic :: Software Development :: Libraries :: Python Modules
Requires-Python: <4.0,>=3.9
Requires-Dist: routelit>=0.4.3
